[
  {
    "Name":"Vinlander",
    "Level": "33",
    "Badges":["dexlander","gomu3"]
  },
  {
    "Name":"Timmys",
    "Level": "31"
  },
  {
    "Name": "Adaryn",
    "Level": "83",
    "Badges":["shirt5","pants4","witch40","broom20","maxdodge","gomu3","omok3","roses","umbrellas","tubes","boards","workgloves","chairs36","pet14","perflights","perfbrella","fence","bluexmas","meso750","knifestrats","lemons300","slipper2","ashes","meso1b","ore100"]
  },
  {
    "Name":"IslanderSage",
    "Level": "32",
    "Badges":["dexlander"]
  },
  {
    "Name":"FionolaV",
    "Level": "35"
  },
  {
    "Name":"IslandSam",
    "Level": "31"
  },
  {
    "Name":"UltraNewb",
    "Level": "31",
    "Alt": "HeroinAddict"
  },
  {
    "Name":"PepeIslander",
    "Level": "30"
  },
  {
    "Name":"babyTalk",
    "Level": "30"
  },
  {
  "Name":"ImmergoId",
  "Level":"35",
  "Badges":["pants2","dexlander","weenjq330","witch30"]
  },
  {
    "Name":"snailee",
    "Level":"37"
  },
  {
    "Name":"analogue",
    "Level":"39"
  },
  {
    "Name":"Navigating",
    "Level":"30"
  },
  {
    "Name":"IslanderIsh",
    "Level":"36"
  },
  {
    "Name":"singa",
    "Level":"30"
  },
  {
    "Name":"Islander0001",
    "Level":"31"
  },
  {
    "Name":"RAPlST",
    "Level":"34"
  },
  {
    "Name":"Gyarulander",
    "Level":"31"
  },
  {
    "Name":"Tubular",
    "Level":"32"
  },
  {
    "Name":"DayDreeam",
    "Level":"32"
  },
  {
    "Name":"NewbieMia",
    "Level":"35"
  },
  {
    "Name":"silliest",
    "Level":"30"
  },
  {
    "Name":"Coinicus",
    "Level":"36"
  },
  {
    "Name":"wtherow",
    "Level":"30"
  },
  {
    "Name":"KokoroKun",
    "Level":"30"
  },
  {
    "Name":"AURALANDER",
    "Level":"30"
  },
  {
    "Name":"Obamanation",
    "Level":"31"
  },
  {
    "Name":"Lahgsmore",
    "Level":"31"
  },
  {
    "Name":"Minus80",
    "Level":"32"
  },
  {
    "Name":"Bobert",
    "Level":"32"
  },
  {
    "Name":"Kasshern",
    "Level":"33"
  },
  {
    "Name":"BillGate",
    "Level":"35"
  },
  {
    "Name":"KillerTofu",
    "Level":"38"
  },
  {
    "Name":"gargant",
    "Level":"42"
  },
  {
    "Name":"VIPOptimus",
    "Level":"30"
  },
  {
    "Name":"TExecutioner",
    "Level":"30"
  },
  {
    "Name":"IslandRogue",
    "Level":"30"
  },
  {
    "Name":"Maperustory",
    "Level":"31"
  },
  {
    "Name":"M4PLEST0RY",
    "Level":"32"
  },
  {
    "Name":"IslandMagi",
    "Level":"32"
  },
  {
    "Name":"Clarence3",
    "Level":"34"
  },
  {
    "Name":"6974892",
    "Level":"34"
  },
  {
    "Name":"imIsolated",
    "Level":"39"
  },
  {
    "Name":"Remain",
    "Level":"30"
  },
  {
    "Name":"AtashiShima",
    "Level":"37"
  },
  {
    "Name":"Lilbuddy",
    "Level":"30"
  },
  {
    "Name":"IslandLife",
    "Level":"30"
  },
  {
    "Name":"Eagoya",
    "Level":"30"
  },
  {
    "Name":"COTTONFARMER",
    "Level":"30"
  },
  {
    "Name":"Blindman",
    "Level":"30"
  },
  {
    "Name":"BenjiPrice",
    "Level":"30"
  },
  {
    "Name":"Sebasdfg3",
    "Level":"32"
  },
  {
    "Name":"LanderLegend",
    "Level":"34"
  },
  {
    "Name":"Atren",
    "Level":"34"
  },
  {
    "Name":"poop1",
    "Level":"40"
  },
  {
    "Name":"ImStranded",
    "Level":"32"
  },
  {
    "Name":"Bodoh",
    "Level":"31"
  },
  {
    "Name":"Sn4ilBasher",
    "Level":"31"
  },
  {
    "Name":"Noll",
    "Level":"46"
  },
  {
    "Name": "natscape",
    "Level": "72",
    "Alias": "Natscape",
    "BadNews": "Opt-out of ranking"
  },
  {
    "Name": "natnavi",
    "Level": "35",
    "BadNews": "Opt-out of ranking",
    "Alt": "Natscape"
  },
  {
    "Name": "nezukochan",
    "Level": "34"
  },
  {
    "Name":"IslandLizard",
    "Level":"44",
    "Badges":["pet14","gomu2"]
  },
  {
    "Name": "Thup",
    "Level": "30"
  },
  {
    "Name": "Lowly",
    "Level": "111",
    "Badges":["meso2b","gomu4","witch40","chairs36","damage1000","roses","fence","omok3","workgloves","perfbrella","strlander","umbrellas","tubes","pet14","shirt3","broom30","ashes","bluexmas","slipper2"]
  },
  {
    "Name": "NamoAmituofo",
    "Level": "111",
    "Alias": "SUPPER",
    "Badges":["gomu4","artifacthunt"]
  },
  {
    "Name": "Annot",
    "Level": "97",
    "Alias": "Ereader",
    "Badges": ["gomu3","pants4","chairs12","slipper3"]
  },
  {
    "Name": "Mooshy",
    "Level": "92",
    "Badges":["gomu3","lemons300"],
    "Since":"2014"
  },
  {
    "Name": "Rally",
    "Level": "85",
    "Alias": "ROBINSON",
    "Badges":["witch30"]
  },
  {
    "Name": "snayl",
    "Level": "83",
    "Alias": "NPCs, Fired",
    "Badges":["artifacthunt"],
    "Since":"2014"
  },
  {
    "Name": "Sawngo",
    "Level": "83",
    "Since":"2015"
  },
  {
    "Name": "IoIzor",
    "Level": "81",
    "BadNews": "Deleted",
    "Since":"2014"
  },
  {
    "Name": "IslandChrizz",
    "Level": "72"
  },
  {
    "Name": "BlueCream",
    "Level": "72"
  },
  {
    "Name": "Chokladkakan",
    "Level": "72",
    "Since":"2014"
  },
  {
    "Name": "BoatlessMonk",
    "Level": "74",
    "Badges":["knifestrats","gomu3","chairs24","roses","fence","damage500","broom20","bluexmas","shirt3","ashes","dexlander","maxdodge","umbrellas","boards","tubes","witch30","weenjq400"]
  },
  {
    "Name": "IslandSlut",
    "Level": "70",
    "Since":"2014"
  },
  {
    "Name": "kitsunyChang",
    "Level": "68"
  },
  {
    "Name": "NewIslander",
    "Level": "70",
    "Since":"2015",
    "Badges":["fence"]
  },
  {
    "Name": "Buikpijn",
    "Level": "69"
  },
  {
    "Name": "DannysIsland",
    "Level": "67",
    "BadNews": "Banned - Botting"
  },
  {
    "Name": "Slain",
    "Level": "66"
  },
  {
    "Name": "PrinceSquidd",
    "Level": "66",
    "Badges":["slipper2"]
  },
  {
    "Name": "sneils",
    "Level": "66",
    "Badges":["fence"]
  },
  {
    "Name": "jung1e",
    "Level": "66",
    "Badges":["artifacthunt"]
  },
  {
    "Name": "saulgoodman",
    "Level": "63",
    "Badges":["fence"],
    "Since":"2015"
  },
  {
    "Name": "Crylou",
    "Level": "63"
  },
  {
    "Name": "DjSammie",
    "Level": "62",
    "Badges":["dynamic"]
  },
  {
    "Name": "MICKYISLAND",
    "Level": "67",
    "Badges":["fence","broom20"]
  },
  {
    "Name": "Snowbelle",
    "Level": "61"
  },
  {
    "Name": "Khebryl",
    "Level": "60",
    "Badges": ["perfbrella"]
  },
  {
    "Name": "Boobs",
    "Level": "60",
    "Since":"2014"
  },
  {
    "Name": "Newbton",
    "Level": "59",
    "Since":"2014"
  },
  {
    "Name": "Beaktoria",
    "Level": "58"
  },
  {
    "Name": "HeroinAddict",
    "Level": "77",
    "Badges":["dynamic","fence","slipper3","pet14","damage800","gomu2","boards","maxdodge","chairs36","weenjq330","broom20","bluexmas","meso250"]
  },
  {
    "Name": "Taeha",
    "Level": "57"
  },
  {
    "Name": "Shylander",
    "Level": "58",
    "Badges":["gomu3","pants4","witch40","perfwand","chairs36","workgloves","omok3","pet14","broom25","fence","damage500","shirt3","slipper2","weenjq330","bluexmas"],
    "Since": "2022",
    "Bio": "Shylander mostly plays challenge modes on Royals, having been a part of Islander, Caveman, World Tour, Legoman, Ironman, and Nostalegion. He usually plays remotely via the steam link Android app. Usually only around during events, he likes the island for the community and long history."
  },
  {
    "Name": "Oahu",
    "Level": "57"
  },
  {
    "Name": "Islander",
    "Level": "56",
    "Alias": "CrimsonClaw",
    "Badges":["dynamic"]
  },
  {
    "Name": "Ekob",
    "Level": "55",
    "Badges":["gomu3","pants4"],
    "Since":"2022"
  },
  {
    "Name": "TheIslander",
    "Level": "55"
  },
  {
    "Name": "Detached",
    "Level": "56"
  },
  {
    "Name": "Barb",
    "Level": "54"
  },
  {
    "Name": "fumumu",
    "Level": "54"
  },
  {
    "Name": "demosthes",
    "Level": "62",
    "Badges":["gomu3","shirt3","damage1000","fence","slipper2"]
  },
  {
    "Name": "Thelslander",
    "Level": "55"
  },
  {
    "Name": "Zheedie",
    "Level": "58"
  },
  {
    "Name": "MotorollaG",
    "Level": "53"
  },
  {
    "Name": "DoctorSnail",
    "Level": "52"
  },
  {
    "Name": "DrewIsland",
    "Level": "52",
    "Badges":["shirt4","slipper2","perfboard","perflights","pants2","gomu3"]
  },
  {
    "Name": "Phack",
    "Level": "52"
  },
  {
    "Name": "DwightK",
    "Level": "53",
    "Badges": ["gomu3","lemons300"]
  },
  {
    "Name": "Anchorage",
    "Level": "52"
  },
  {
    "Name": "KillingTime",
    "Level": "52"
  },
  {
    "Name": "ShimaPanda",
    "Level": "52"
  },
  {
    "Name": "YoungLePopo",
    "Level": "51",
    "Badges":["fence"]
  },
  {
    "Name": "omgwow",
    "Level": "51"
  },
  {
    "Name": "Permit",
    "Level": "51",
    "Badges":["witch30"]
  },
  {
    "Name": "Delfino",
    "Level": "52",
    "Badges":["fence","gomu4"]
  },
  {
    "Name": "BananaIsland",
    "Level": "51",
    "Badges":["dynamic"]
  },
  {
    "Name": "Evacchi",
    "Level": "51",
    "Badges":["dynamic"]
  },
  {
    "Name": "WatIsHarbor",
    "Level": "51",
    "BadNews": "Took the Boat in 2017",
    "Since":"2015"
  },
  {
    "Name": "WasteOfTime",
    "Level": "51"
  },
  {
    "Name": "IslandKush",
    "Level": "52"
  },
  {
    "Name": "Bella",
    "Level": "50"
  },
  {
    "Name": "Lonelymoo",
    "Level": "50"
  },
  {
    "Name": "Vallug",
    "Level": "50"
  },
  {
    "Name": "Homebone",
    "Level": "50"
  },
  {
    "Name": "Setsunax3",
    "Level": "50"
  },
  {
    "Name": "Slowride",
    "Level": "50"
  },
  {
    "Name": "Ague",
    "Level": "50"
  },
  {
    "Name": "Pienor",
    "Alias":"Fundlander",
    "Alt":"Wienor",
    "Level": "64",
    "Badges":["damage1000"]
  },
  {
    "Name": "Oreliel",
    "Level": "49"
  },
  {
    "Name": "VillageIdiot",
    "Level": "49",
    "Badges":["fence"]
  },
  {
    "Name": "Frenzeys",
    "Level": "49"
  },
  {
    "Name": "DragonAsh",
    "Level": "48"
  },
  {
    "Name": "Woogie",
    "Level": "48"
  },
  {
    "Name": "Daxos",
    "Level": "48",
    "Since":"2014"
  },
  {
    "Name": "Staying",
    "Level": "48"
  },
  {
    "Name": "MissedDaBoat",
    "Level": "47"
  },
  {
    "Name": "mendroid",
    "Level": "47"
  },
  {
    "Name": "WhiteCaviar",
    "Level": "47"
  },
  {
    "Name": "islandmelan",
    "Level": "47",
    "Badges":["fence"]
  },
  {
    "Name": "Vigi",
    "Level": "53"
  },
  {
    "Name": "noob4ever",
    "Level": "47"
  },
  {
    "Name": "PalmSap",
    "Level": "47"
  },
  {
    "Name": "Aborigine",
    "Level": "47",
    "Since":"2014"
  },
  {
    "Name": "snapplesx",
    "Level": "48"
  },
  {
    "Name": "Tails183",
    "Level": "46"
  },
  {
    "Name": "YesImaN00b",
    "Level": "46",
    "Badges":["fence"]
  },
  {
    "Name": "IslandVanity",
    "Level": "46"
  },
  {
    "Name": "minitaro",
    "Level": "46"
  },
  {
    "Name": "SnowyHeartZ",
    "Level": "46"
  },
  {
    "Name": "SnailKid",
    "Level": "45"
  },
  {
    "Name": "cowe",
    "Level": "46"
  },
  {
    "Name": "Imlost",
    "Level": "45"
  },
  {
    "Name": "virus17",
    "Level": "45"
  },
  {
    "Name": "Abolbo",
    "Level": "45"
  },
  {
    "Name": "Floater",
    "Level": "42",
    "BadNews": "Banned - RWT"
  },
  {
    "Name": "StarTropics",
    "Level": "62",
    "Badges": ["damage1000","chairs24","gomu3","pet14","omok3","weenjq400","broom20","bluexmas","shirt2"]
  },
  {
    "Name": "Ataynep",
    "Level": "44"
  },
  {
    "Name": "Xochi",
    "Level": "44"
  },
  {
    "Name": "Catmint",
    "Level": "44"
  },
  {
    "Name": "15kg",
    "Level": "44",
    "BadNews": "Banned - Account Sharing"
  },
  {
    "Name": "NoSkills",
    "Level": "45"
  },
  {
    "Name": "Chibilander",
    "Level": "44"
  },
  {
    "Name": "Schwer",
    "Level": "44"
  },
  {
    "Name": "Genderfreak",
    "Level": "44"
  },
  {
    "Name": "iHitSnail",
    "Level": "44"
  },
  {
    "Name": "MewIslander",
    "Level": "43"
  },
  {
    "Name": "Valtarre",
    "Level": "60",
    "Badges":["dexlander","damage300","gomu2","fence","lemons300","omok3","weenjq400","bluexmas","chairs12","shirt2","perfbeg"]
  },
  {
    "Name": "inland",
    "Level": "43"
  },
  {
    "Name": "Hoodwinker",
    "Level": "43"
  },
  {
    "Name": "Lerick",
    "Level": "43"
  },
  {
    "Name": "Isleturi",
    "Level": "43"
  },
  {
    "Name": "lovegone",
    "Level": "43"
  },
  {
    "Name": "MayFlowers",
    "Level": "43"
  },
  {
    "Name": "BegPride",
    "Level": "43",
    "Badges":["pants3"]
  },
  {
    "Name": "BootyClapper",
    "Level": "42"
  },
  {
    "Name": "RyuuNoob",
    "Level": "42"
  },
  {
    "Name": "Wavecap",
    "Level": "42"
  },
  {
    "Name": "Basically",
    "Level": "42",
    "Since":"2015"
  },
  {
    "Name": "Snooze",
    "Level": "44"
  },
  {
    "Name": "gunpoint",
    "Level": "42",
    "Badges":["witch30"]
  },
  {
    "Name": "Relate",
    "Level": "42"
  },
  {
    "Name": "MrBeef",
    "Since": "2018",
    "Level": "41"
  },
  {
    "Name": "lootystays",
    "Level": "41"
  },
  {
    "Name": "Cowbelle",
    "Level": "41"
  },
  {
    "Name": "juman",
    "Level": "41"
  },
  {
    "Name": "LowIy",
    "Level": "41",
    "Alt": "Lowly",
    "Badges":["magelander"]
  },
  {
    "Name": "Ramleh",
    "Level": "41"
  },
  {
    "Name": "Perfidious",
    "Level": "41"
  },
  {
    "Name": "Granpulse",
    "Level": "41"
  },
  {
    "Name": "ZakoZantern",
    "Level": "50",
    "Badges":["dynamic","gomu2","shirt3","pet14","workgloves","witch40","weenjq500","bluexmas","chairs12","lemons300"]
  },
  {
    "Name": "IslandBoyz",
    "Level": "40"
  },
  {
    "Name": "Bream",
    "Level": "40"
  },
  {
    "Name": "DevOnIsland",
    "Level": "58",
    "Badges":["dynamic","gomu3","witch40","shirt2","lemons300","damage300","pet14","omok3","weenjq330","workgloves","pants2","broom20","chairs12","ashes","bluexmas","perfbeg"]
  },
  {
    "Name": "Tsukishima",
    "Level": "40",
    "Badges":["perfboard"]
  },
  {
    "Name": "Ichihime",
    "Level": "40"
  },
  {
    "Name": "Eurobeatnik",
    "Level": "40"
  },
  {
    "Name": "philswife",
    "Level": "40"
  },
  {
    "Name": "JohnLander",
    "Level": "40"
  },
  {
    "Name": "TRAPBOI",
    "Level": "41",
    "Alt":"Wienor"
  },
  {
    "Name": "Noobtando",
    "Level": "39"
  },
  {
    "Name": "OwenWasHer",
    "Level": "39"
  },
  {
    "Name": "BadDecision",
    "Level": "39"
  },
  {
    "Name": "Exthene",
    "Level": "39"
  },
  {
    "Name": "BARF",
    "Level": "39"
  },
  {
    "Name": "Gutter",
    "Level": "39"
  },
  {
    "Name": "Secluded",
    "Level": "39"
  },
  {
    "Name": "Boatphobia",
    "Level": "39"
  },
  {
    "Name": "Lalafae",
    "Level": "39"
  },
  {
    "Name": "NaughtyHoe",
    "Level": "39"
  },
  {
    "Name": "Father",
    "Level": "38"
  },
  {
    "Name": "deadppl",
    "Level": "38",
    "BadNews": "Banned - Botting"
  },
  {
    "Name": "Wienor",
    "Level": "38"
  },
  {
    "Name": "SoreTooth",
    "Level": "38"
  },
  {
    "Name": "ooYUIoo",
    "Level": "38"
  },
  {
    "Name": "IslandMyCity",
    "Level": "38"
  },
  {
    "Name": "TaZLaNDeR",
    "Level": "38"
  },
  {
    "Name": "Fortyeight",
    "Level": "38"
  },
  {
    "Name": "ChiefSmeng",
    "Level": "38"
  },
  {
    "Name": "Nauset",
    "Level": "38"
  },
  {
    "Name": "Deryn",
    "Level": "43",
    "Alt": "Adaryn",
    "Badges":["magelander"]
  },
  {
    "Name": "nuber",
    "Level": "38"
  },
  {
    "Name": "Lelador",
    "Level": "38"
  },
  {
    "Name": "IslanderCye",
    "Level": "38"
  },
  {
    "Name": "tyeon",
    "Level": "38"
  },
  {
    "Name": "Kowlar",
    "Level": "38"
  },
  {
    "Name": "2ManyShrooms",
    "Level": "38",
    "Badges":["fence"]
  },
  {
    "Name": "Stratagem",
    "Level": "38"
  },
  {
    "Name": "Niikasd",
    "Level": "40",
    "Badges":["shirt4"]
  },
  {
    "Name": "daredemonai",
    "Level": "38"
  },
  {
    "Name": "Speklap",
    "Level": "38"
  },
  {
    "Name": "xSnail",
    "Level": "37"
  },
  {
    "Name": "SadakoChan",
    "Level": "37"
  },
  {
    "Name": "Laxz",
    "Level": "37",
    "Badges":["shirt5"]
  },
  {
    "Name": "Takoa",
    "Level": "37"
  },
  {
    "Name": "Sincashy",
    "Level": "37"
  },
  {
    "Name": "Bwek",
    "Level": "37"
  },
  {
    "Name": "Noobley",
    "Level": "37",
    "Badges":["fence"]
  },
  {
    "Name": "Homemade",
    "Level": "37"
  },
  {
    "Name": "Adagaki",
    "Level": "37",
    "Alt":"Wienor"
  },
  {
    "Name": "Jollybaby",
    "Level": "38"
  },
  {
    "Name": "Shimon",
    "Level": "37"
  },
  {
    "Name": "DDorian",
    "Level": "37"
  },
  {
    "Name": "BillyMaize1",
    "Level": "37"
  },
  {
    "Name": "steb",
    "Level": "37"
  },
  {
    "Name": "IslandAneu",
    "Level": "37"
  },
  {
    "Name": "Shr00m",
    "Level": "36"
  },
  {
    "Name": "Kidou",
    "Level": "36"
  },
  {
    "Name": "IdleN---a",
    "Level": "36"
  },
  {
    "Name": "BestBuddy",
    "Level": "36"
  },
  {
    "Name": "Soriak",
    "Level": "38"
  },
  {
    "Name": "NoBoat",
    "Level": "36"
  },
  {
    "Name": "zagex",
    "Level": "36"
  },
  {
    "Name": "SNAIL",
    "Level": "35"
  },
  {
    "Name": "StrandedHere",
    "Level": "35"
  },
  {
    "Name": "PermaIsland",
    "Level": "35"
  },
  {
    "Name": "Poop37",
    "Level": "35"
  },
  {
    "Name": "IslandMadnes",
    "Level": "35"
  },
  {
    "Name": "ReixoLander",
    "Level": "35"
  },
  {
    "Name": "Memphon",
    "Level": "35"
  },
  {
    "Name": "BL00",
    "Level": "35"
  },
  {
    "Name": "Boatophobic",
    "Level": "35"
  },
  {
    "Name": "iStayHere",
    "Level": "35"
  },
  {
    "Name": "IslandDango",
    "Level": "35"
  },
  {
    "Name": "Stumper",
    "Level": "35"
  },
  {
    "Name": "Hots",
    "Level": "35",
    "Since":"2015"
  },
  {
    "Name": "V0id",
    "Level": "35"
  },
  {
    "Name": "TheAmateur",
    "Level": "35"
  },
  {
    "Name": "kicsi",
    "Level": "35"
  },
  {
    "Name": "IslanderKarp",
    "Level": "38"
  },
  {
    "Name": "DumbIsland",
    "Level": "38"
  },
  {
    "Name": "Vaudeville",
    "Level": "35"
  },
  {
    "Name": "VaudeviIle",
    "Level": "31"
  },
  {
    "Name": "StareDecisis",
    "Level": "34"
  },
  {
    "Name": "OneSlapMan",
    "Level": "34"
  },
  {
    "Name": "NoobGlitch",
    "Level": "34"
  },
  {
    "Name": "IwillStay",
    "Level": "35"
  },
  {
    "Name": "FULLDEXME",
    "Level": "34"
  },
  {
    "Name": "Eyesland",
    "Level": "34"
  },
  {
    "Name": "Auevaria",
    "Level": "34"
  },
  {
    "Name": "Gooods",
    "Level": "34"
  },
  {
    "Name": "Protato",
    "Level": "34"
  },
  {
    "Name": "IslandStory",
    "Level": "37"
  },
  {
    "Name": "iPokeSnails",
    "Level": "34",
    "Badges":["fence"]
  },
  {
    "Name": "openpro",
    "Level": "34"
  },
  {
    "Name": "BenHammer",
    "Level": "34",
    "Badges":["fence"]
  },
  {
    "Name": "Blueisland",
    "Level": "34",
    "Alt": "Bluecream"
  },
  {
    "Name": "Puberty",
    "Level": "34",
    "Badges":["fence"]
  },
  {
    "Name": "Gump",
    "Level": "34"
  },
  {
    "Name": "IslandMage",
    "Level": "34",
    "Badges":["magelander","fence"]
  },
  {
    "Name": "Moganji",
    "Level": "40"
  },
  {
    "Name": "susube12",
    "Level": "33"
  },
  {
    "Name": "ThislsHome",
    "Level": "33"
  },
  {
    "Name": "YuriGod",
    "Level": "34"
  },
  {
    "Name": "Shave",
    "Level": "33"
  },
  {
    "Name": "RXIslander",
    "Level": "39"
  },
  {
    "Name": "Tailu",
    "Level": "33"
  },
  {
    "Name": "LCH2",
    "Level": "33"
  },
  {
    "Name": "WarSlug",
    "Level": "33"
  },
  {
    "Name": "Taslynn",
    "Level": "33"
  },
  {
    "Name": "GGInInDer",
    "Level": "33"
  },
  {
    "Name": "Eilander",
    "Level": "33"
  },
  {
    "Name": "EvilBetty",
    "Level": "33"
  },
  {
    "Name": "j3ll79",
    "Level": "33"
  },
  {
    "Name": "NomNomNomNom",
    "Level": "33"
  },
  {
    "Name": "Voldsoy",
    "Level": "61",
    "Alias":"Ailand",
    "Badges":["weenjq400"]
  },
  {
    "Name": "Nooburt",
    "Level": "32"
  },
  {
    "Name": "TrumpsBack",
    "Level": "32"
  },
  {
    "Name": "EverIslander",
    "Level": "32"
  },
  {
    "Name": "NoBoater",
    "Level": "32"
  },
  {
    "Name": "Villager",
    "Level": "32"
  },
  {
    "Name": "Landzerr",
    "Level": "32",
    "BadNews": "Banned - Fly Hacks in JQ"
  },
  {
    "Name": "Jale",
    "Level": "32"
  },
  {
    "Name": "Harutsuki",
    "Level": "32"
  },
  {
    "Name": "BaDonkaDonk",
    "Level": "32"
  },
  {
    "Name": "IOSYS",
    "Level": "32"
  },
  {
    "Name": "Deidara",
    "Level": "33"
  },
  {
    "Name": "Chimney",
    "Level": "32"
  },
  {
    "Name": "Bralette",
    "Level": "32"
  },
  {
    "Name": "Whack",
    "Level": "32"
  },
  {
    "Name": "LoveIsland",
    "Level": "41"
  },
  {
    "Name": "l3asic",
    "Level": "32"
  },
  {
    "Name": "HotThot",
    "Level": "33"
  },
  {
    "Name": "NekoStuffs",
    "Level": "32"
  },
  {
    "Name": "Vista",
    "Level": "32"
  },
  {
    "Name": "NuIIbyte",
    "Level": "34",
    "Alias": "SirNyanta"
  },
  {
    "Name": "iCanAssist",
    "Level": "32"
  },
  {
    "Name": "Deity",
    "Level": "32"
  },
  {
    "Name": "ShotCaller",
    "Level": "31",
    "Alt": "Annot"
  },
  {
    "Name": "TurtleHermlt",
    "Level": "31"
  },
  {
    "Name": "Isolander",
    "Level": "31"
  },
  {
    "Name": "islandmop",
    "Level": "31"
  },
  {
    "Name": "IslandLord",
    "Level": "31"
  },
  {
    "Name": "DiJeeSammie",
    "Level": "31"
  },
  {
    "Name": "Deported",
    "Level": "31"
  },
  {
    "Name": "Apis",
    "Level": "31"
  },
  {
    "Name": "Islanderrs",
    "Level": "31"
  },
  {
    "Name": "geologic",
    "Level": "37"
  },
  {
    "Name": "DBIslander",
    "Level": "31"
  },
  {
    "Name": "VoidOfBliss",
    "Level": "31"
  },
  {
    "Name": "TnnT",
    "Level": "31"
  },
  {
    "Name": "SnailEmperor",
    "Level": "31"
  },
  {
    "Name": "page99",
    "Level": "31"
  },
  {
    "Name": "Schnitzel",
    "Level": "31"
  },
  {
    "Name": "Kendria",
    "Level": "31"
  },
  {
    "Name": "SlappyJr",
    "Level": "33"
  },
  {
    "Name": "iCantSwim",
    "Level": "31"
  },
  {
    "Name": "IslanderJoel",
    "Level": "32",
    "Since":"2015"
  },
  {
    "Name": "Kasuto",
    "Level": "31",
    "Badges":["fence"]
  },
  {
    "Name": "Crazily",
    "Level": "31"
  },
  {
    "Name": "Quitlander",
    "Level": "31"
  },
  {
    "Name": "Nature",
    "Level": "31"
  },
  {
    "Name": "Accel",
    "Level": "31",
    "Since":"2014"
  },
  {
    "Name": "COM002",
    "Level": "32"
  },
  {
    "Name": "PenIsland",
    "Level": "31"
  },
  {
    "Name": "MereCat",
    "Level": "35"
  },
  {
    "Name": "NoPointer",
    "Level": "35",
    "Badges":["nopointer"]
  },
  {
    "Name": "FatGuyIRL",
    "Level": "31"
  },
  {
    "Name": "Snailblazer",
    "Level": "30"
  },
  {
    "Name": "FatherID",
    "Level": "31"
  },
  {
    "Name": "IslandForeve",
    "Level": "30"
  },
  {
    "Name": "CalledShot",
    "Level": "30"
  },
  {
    "Name": "Grylls",
    "Level": "30"
  },
  {
    "Name": "Fabulous",
    "Level": "30"
  },
  {
    "Name": "Oniisan",
    "Level": "30"
  },
  {
    "Name": "safehouse",
    "Level": "30",
    "Alt": "Annot"
  },
  {
    "Name": "SnailQueen",
    "Level": "30"
  },
  {
    "Name": "slit",
    "Level": "30"
  },
  {
    "Name": "PhilJackson",
    "Level": "30"
  },
  {
    "Name": "NoBoatJoe",
    "Level": "30"
  },
  {
    "Name": "Nekosei",
    "Level": "30"
  },
  {
    "Name": "Lentil",
    "Level": "30"
  },
  {
    "Name": "Gids",
    "Level": "30"
  },
  {
    "Name": "EiIander",
    "Level": "30"
  },
  {
    "Name": "j3lly9",
    "Level": "30"
  },
  {
    "Name": "wulfy",
    "Level": "30"
  },
  {
    "Name": "jelly",
    "Level": "30"
  },
  {
    "Name": "RainbowH0e",
    "Level": "30"
  },
  {
    "Name": "JulesIsland",
    "Level": "30"
  },
  {
    "Name": "Kuchkii",
    "Level": "30"
  },
  {
    "Name": "Neislander",
    "Level": "30"
  },
  {
    "Name": "Aquaroad",
    "Level": "30"
  },
  {
    "Name": "Moirai",
    "Level": "30"
  },
  {
    "Name": "TheFoggiest",
    "Level": "30"
  },
  {
    "Name": "Ecliptic",
    "Level": "30"
  },
  {
    "Name": "Striver",
    "Level": "30"
  },
  {
    "Name": "Flux",
    "Level": "30",
    "Badges":["fence"]
  },
  {
    "Name": "wargreymon",
    "Level": "30"
  },
  {
    "Name": "Command",
    "Level": "30"
  },
  {
    "Name": "sidemirrors",
    "Level": "30"
  },
  {
    "Name": "hoejoe",
    "Level": "30"
  },
  {
    "Name": "Ambivert",
    "Level": "30"
  },
  {
    "Name": "Shellcaster",
    "Level": "30",
    "Alt": "Shylander",
    "Badges":["magelander"]
  },
  {
    "Name": "ShyIander",
    "Level": "30",
    "Alt": "Shylander"
  },
  {
    "Name": "Native",
    "Level": "30"
  },
  {
    "Name": "MeStuck",
    "Level": "30"
  },
  {
    "Name": "Stoven",
    "Level": "30"
  },
  {
    "Name": "Gumptwo",
    "Level": "32"
  },
  {
    "Name": "IslandTessa",
    "Level": "30"
  },
  {
    "Name": "BOIBUTT",
    "Level": "30",
    "Alt":"Wienor"
  }
]
